setup.cfg
setup.py
mrot/__init__.py
mrot/__main__.py
mrot/cli.py
mrot/imdb.py
mrot.egg-info/PKG-INFO
mrot.egg-info/SOURCES.txt
mrot.egg-info/dependency_links.txt
mrot.egg-info/entry_points.txt
mrot.egg-info/not-zip-safe
mrot.egg-info/requires.txt
mrot.egg-info/top_level.txt
mrot/test/__init__.py
mrot/test/imdb_test.py