Metadata-Version: 1.0
Name: mrot
Version: 0.4
Summary: Movie ratings over time
Home-page: UNKNOWN
Author: Arthur Brenaut
Author-email: arthur.brenaut@gmail.com
License: UNKNOWN
Platform: UNKNOWN
